TotalDepth/DeTif.py
TotalDepth/PlotLogs.py
TotalDepth/__init__.py
TotalDepth/BIT/ReadBIT.py
TotalDepth/BIT/ToLAS.py
TotalDepth/BIT/__init__.py
TotalDepth/DAT/DAT_parser.py
TotalDepth/DAT/ReadDATFiles.py
TotalDepth/DAT/__init__.py
TotalDepth/LAS/LASToHTML.py
TotalDepth/LAS/ReadLASFiles.py
TotalDepth/LAS/__init__.py
TotalDepth/LAS/core/LASConstants.py
TotalDepth/LAS/core/LASRead.py
TotalDepth/LAS/core/WriteLAS.py
TotalDepth/LAS/core/__init__.py
TotalDepth/LIS/DumpFrameSet.py
TotalDepth/LIS/Index.py
TotalDepth/LIS/LisToHtml.py
TotalDepth/LIS/PlotLogPasses.py
TotalDepth/LIS/ProcLISPath.py
TotalDepth/LIS/RandomFrameSetRead.py
TotalDepth/LIS/ScanLogiData.py
TotalDepth/LIS/ScanLogiRec.py
TotalDepth/LIS/ScanPhysRec.py
TotalDepth/LIS/TableHistogram.py
TotalDepth/LIS/ToLAS.py
TotalDepth/LIS/__init__.py
TotalDepth/LIS/lis_cmn_cmd_opts.py
TotalDepth/LIS/core/EngVal.py
TotalDepth/LIS/core/File.py
TotalDepth/LIS/core/FileIndexer.py
TotalDepth/LIS/core/FrameSet.py
TotalDepth/LIS/core/GenLisFiles.py
TotalDepth/LIS/core/IndexBuiltIn.py
TotalDepth/LIS/core/LisGen.py
TotalDepth/LIS/core/LogPass.py
TotalDepth/LIS/core/LogiRec.py
TotalDepth/LIS/core/Mnem.py
TotalDepth/LIS/core/NamedStruct.py
TotalDepth/LIS/core/PhysRec.py
TotalDepth/LIS/core/RawStream.py
TotalDepth/LIS/core/RepCode.py
TotalDepth/LIS/core/Rle.py
TotalDepth/LIS/core/TifMarker.py
TotalDepth/LIS/core/Type01Plan.py
TotalDepth/LIS/core/Units.py
TotalDepth/LIS/core/XNAM.py
TotalDepth/LIS/core/__init__.py
TotalDepth/LIS/core/cFrameSet.cpython-37m-darwin.so
TotalDepth/LIS/core/cRepCode.cpython-37m-darwin.so
TotalDepth/LIS/core/cpRepCode.cpython-37m-darwin.so
TotalDepth/LIS/core/pRepCode.py
TotalDepth/LIS/core/src/cp/cpLISRepCode.cpp
TotalDepth/LIS/core/src/cp/cpLISRepCode.h
TotalDepth/LIS/core/src/cpp/LISRepCode.cpp
TotalDepth/LIS/core/src/cpp/LISRepCode.h
TotalDepth/LIS/core/src/cython/cFrameSet.pyx
TotalDepth/LIS/core/src/cython/cRepCode.pyx
TotalDepth/RP66V1/IndexPickle.py
TotalDepth/RP66V1/IndexXML.py
TotalDepth-0.4.0.dist-info/AUTHORS.rst
TotalDepth-0.4.0.dist-info/LICENCE
TotalDepth-0.4.0.dist-info/METADATA
TotalDepth-0.4.0.dist-info/WHEEL
TotalDepth-0.4.0.dist-info/entry_points.txt
TotalDepth-0.4.0.dist-info/top_level.txt
TotalDepth-0.4.0.dist-info/RECORD
