Metadata-Version: 2.1
Name: TotalDepth
Version: 0.4.0
Summary: TotalDepth is a software collection that can process petrophysical data such as wireline logs.
Home-page: https://github.com/paulross/TotalDepth
Author: Paul Ross
Author-email: apaulross@gmail.com
License: GPLv2
Keywords: TotalDepth
Platform: UNKNOWN
Classifier: Development Status :: 5 - Production/Stable
Classifier: Intended Audience :: Developers
Classifier: License :: OSI Approved :: GNU General Public License v2 (GPLv2)
Classifier: Natural Language :: English
Classifier: Programming Language :: Python :: 3
Classifier: Programming Language :: Python :: 3.7
Classifier: Programming Language :: Python :: 3.8
Classifier: Programming Language :: Python :: 3.9
License-File: LICENCE
License-File: AUTHORS.rst
Requires-Dist: Cython
Requires-Dist: Pillow
Requires-Dist: beautifulsoup4
Requires-Dist: colorama
Requires-Dist: lxml
Requires-Dist: numpy
Requires-Dist: psutil
Requires-Dist: requests
